pymelos/__init__.py
pymelos/__main__.py
pymelos/compat.py
pymelos/errors.py
pymelos/py.typed
pymelos/types.py
pymelos/cli/__init__.py
pymelos/cli/__main__.py
pymelos/cli/app.py
pymelos/cli/commands/__init__.py
pymelos/cli/commands/init.py
pymelos/cli/output/table.py
pymelos/commands/__init__.py
pymelos/commands/add.py
pymelos/commands/base.py
pymelos/commands/bootstrap.py
pymelos/commands/changed.py
pymelos/commands/clean.py
pymelos/commands/exec.py
pymelos/commands/list.py
pymelos/commands/release.py
pymelos/commands/run.py
pymelos/commands/version.py
pymelos/config/__init__.py
pymelos/config/loader.py
pymelos/config/schema.py
pymelos/execution/__init__.py
pymelos/execution/parallel.py
pymelos/execution/results.py
pymelos/execution/runner.py
pymelos/filters/__init__.py
pymelos/filters/chain.py
pymelos/filters/ignore.py
pymelos/filters/scope.py
pymelos/filters/since.py
pymelos/git/__init__.py
pymelos/git/changes.py
pymelos/git/commits.py
pymelos/git/repo.py
pymelos/git/tags.py
pymelos/uv/__init__.py
pymelos/uv/client.py
pymelos/uv/publish.py
pymelos/uv/sync.py
pymelos/versioning/__init__.py
pymelos/versioning/changelog.py
pymelos/versioning/conventional.py
pymelos/versioning/semver.py
pymelos/versioning/updater.py
pymelos/workspace/__init__.py
pymelos/workspace/discovery.py
pymelos/workspace/graph.py
pymelos/workspace/package.py
pymelos/workspace/workspace.py
pymelos-0.1.4.dist-info/METADATA
pymelos-0.1.4.dist-info/WHEEL
pymelos-0.1.4.dist-info/entry_points.txt
pymelos-0.1.4.dist-info/licenses/LICENSE
pymelos-0.1.4.dist-info/RECORD
