Metadata-Version: 2.4
Name: pymelos
Version: 0.1.4
Summary: Python monorepo manager
Project-URL: Homepage, https://github.com/y3l1n4ung/pymelos
Project-URL: Repository, https://github.com/y3l1n4ung/pymelos
Project-URL: Issues, https://github.com/y3l1n4ung/pymelos/issues
Author: Ye Lin Aung
License: MIT
License-File: LICENSE
Keywords: env,management,monorepo,python,uv,workspace
Classifier: Development Status :: 3 - Alpha
Classifier: Environment :: Console
Classifier: Intended Audience :: Developers
Classifier: License :: OSI Approved :: MIT License
Classifier: Operating System :: OS Independent
Classifier: Programming Language :: Python :: 3
Classifier: Programming Language :: Python :: 3.10
Classifier: Programming Language :: Python :: 3.11
Classifier: Programming Language :: Python :: 3.12
Classifier: Programming Language :: Python :: 3.13
Classifier: Topic :: Software Development :: Build Tools
Classifier: Typing :: Typed
Requires-Python: >=3.10
Requires-Dist: pydantic>=2.0.0
Requires-Dist: pyyaml>=6.0.0
Requires-Dist: rich>=13.0.0
Requires-Dist: tomli>=2.0.0; python_version < '3.11'
Requires-Dist: typer>=0.15.0
Provides-Extra: dev
Requires-Dist: commitizen>=4.0.0; extra == 'dev'
Requires-Dist: pre-commit>=4.0.0; extra == 'dev'
Requires-Dist: pytest-asyncio>=0.24.0; extra == 'dev'
Requires-Dist: pytest-cov>=6.0.0; extra == 'dev'
Requires-Dist: pytest>=8.0.0; extra == 'dev'
Requires-Dist: python-dotenv>=1.0.0; extra == 'dev'
Requires-Dist: ruff>=0.8.0; extra == 'dev'
